tests/__init__.py
tests/test_helpers.py
tests/test_indexes.py
tests/test_nlp.py
tests/test_preprocessing.py
tests/test_representation.py
tests/test_types.py
tests/test_visualization.py
texthero/__init__.py
texthero/_helper.py
texthero/_types.py
texthero/nlp.py
texthero/preprocessing.py
texthero/representation.py
texthero/stopwords.py
texthero/visualization.py
textherox-1.2.0.dist-info/LICENSE
textherox-1.2.0.dist-info/METADATA
textherox-1.2.0.dist-info/WHEEL
textherox-1.2.0.dist-info/top_level.txt
textherox-1.2.0.dist-info/RECORD
