Metadata-Version: 2.1
Name: textherox
Version: 1.2.0
Summary: Text preprocessing, representation and visualization from zero to hero.
Home-page: https://github.com/jbesomi/texthero
Author: Jonathan Besomi || Maintained by Patrick Phat
License: MIT
Project-URL: Documentation, https://texthero.org/
Project-URL: Source Code, https://github.com/jbesomi/texthero
Project-URL: Bug Tracker, https://github.com/jbesomi/texthero/issues
Keywords: text mining,text preprocessing,text representation,text visualization
Classifier: Development Status :: 3 - Alpha
Classifier: License :: OSI Approved :: MIT License
Classifier: Intended Audience :: Developers
Classifier: Programming Language :: Python
Classifier: Natural Language :: English
Classifier: Topic :: Scientific/Engineering
Requires-Python: >=3.6.1
License-File: LICENSE
Requires-Dist: numpy (>=1.17)
Requires-Dist: scikit-learn (>=0.22)
Requires-Dist: spacy (<3.0.0)
Requires-Dist: tqdm (>=4.3)
Requires-Dist: nltk (>=3.3)
Requires-Dist: plotly (>=4.2.0)
Requires-Dist: pandas (>=1.0.2)
Requires-Dist: wordcloud (>=1.5.0)
Requires-Dist: gensim (<5,>4.0)
Requires-Dist: matplotlib (>=3.1.0)
Provides-Extra: dev
Requires-Dist: black (==19.10b0) ; extra == 'dev'
Requires-Dist: pytest (>=4.0.0) ; extra == 'dev'
Requires-Dist: Sphinx (>=3.0.3) ; extra == 'dev'
Requires-Dist: sphinx-markdown-builder (>=0.5.4) ; extra == 'dev'
Requires-Dist: recommonmark (>=0.6.0) ; extra == 'dev'
Requires-Dist: nbsphinx ; extra == 'dev'
Requires-Dist: parameterized (>=0.7.4) ; extra == 'dev'
Requires-Dist: coverage ; extra == 'dev'
Requires-Dist: pre-commit ; extra == 'dev'
Requires-Dist: pandas (>=1.1.0) ; extra == 'dev'
